[
    {
        "certificateNumber": "SHM-0046",
        "name": "Cut Nyak Dien",
        "location": "Jl. Pahlawan No. 73, Jakarta",
        "area": 2602
    },
    {
        "certificateNumber": "SHM-0047",
        "name": "Hasanuddin",
        "location": "Jl. Melati No. 80, Bogor",
        "area": 2639
    },
    {
        "certificateNumber": "SHM-0048",
        "name": "Pattimura",
        "location": "Jl. Mawar No. 87, Bandung",
        "area": 2676
    },
    {
        "certificateNumber": "SHM-0049",
        "name": "Imam Bonjol",
        "location": "Jl. Kenanga No. 94, Bekasi",
        "area": 2713
    },
    {
        "certificateNumber": "SHM-0050",
        "name": "Wahidin",
        "location": "Jl. Cendana No. 101, Depok",
        "area": 2750
    },
    {
        "certificateNumber": "SHM-0051",
        "name": "Agus Salim",
        "location": "Jl. Merdeka No. 108, Tangerang",
        "area": 2787
    },
    {
        "certificateNumber": "SHM-0052",
        "name": "Ki Hajar",
        "location": "Jl. Sudirman No. 115, Surabaya",
        "area": 2824
    },
    {
        "certificateNumber": "SHM-0053",
        "name": "Tjokroaminoto",
        "location": "Jl. Diponegoro No. 122, Semarang",
        "area": 2861
    },
    {
        "certificateNumber": "SHM-0054",
        "name": "Sutomo",
        "location": "Jl. Gajah Mada No. 129, Yogyakarta",
        "area": 2898
    },
    {
        "certificateNumber": "SHM-0055",
        "name": "Juanda",
        "location": "Jl. Ahmad Yani No. 136, Malang",
        "area": 2535
    },
    {
        "certificateNumber": "SHM-0056",
        "name": "Sjahrir",
        "location": "Jl. Pahlawan No. 143, Medan",
        "area": 2572
    },
    {
        "certificateNumber": "SHM-0057",
        "name": "Dewantara",
        "location": "Jl. Melati No. 150, Makassar",
        "area": 2609
    },
    {
        "certificateNumber": "SHM-0058",
        "name": "Ranggawarsita",
        "location": "Jl. Mawar No. 157, Denpasar",
        "area": 2646
    },
    {
        "certificateNumber": "SHM-0059",
        "name": "Yos Sudarso",
        "location": "Jl. Kenanga No. 164, Solo",
        "area": 2683
    },
    {
        "certificateNumber": "SHM-0060",
        "name": "Pierre Tendean",
        "location": "Jl. Cendana No. 171, Cirebon",
        "area": 2720
    },
    {
        "certificateNumber": "SHM-0061",
        "name": "Soekarno",
        "location": "Jl. Merdeka No. 178, Jakarta",
        "area": 2757
    },
    {
        "certificateNumber": "SHM-0062",
        "name": "Hatta",
        "location": "Jl. Sudirman No. 185, Bogor",
        "area": 2794
    },
    {
        "certificateNumber": "SHM-0063",
        "name": "Sudirman",
        "location": "Jl. Diponegoro No. 192, Bandung",
        "area": 2831
    },
    {
        "certificateNumber": "SHM-0064",
        "name": "Kartini",
        "location": "Jl. Gajah Mada No. 199, Bekasi",
        "area": 2868
    },
    {
        "certificateNumber": "SHM-0065",
        "name": "Diponegoro",
        "location": "Jl. Ahmad Yani No. 206, Depok",
        "area": 2505
    },
    {
        "certificateNumber": "SHM-0066",
        "name": "Cut Nyak Dien",
        "location": "Jl. Pahlawan No. 213, Tangerang",
        "area": 2542
    },
    {
        "certificateNumber": "SHM-0067",
        "name": "Hasanuddin",
        "location": "Jl. Melati No. 220, Surabaya",
        "area": 2579
    },
    {
        "certificateNumber": "SHM-0068",
        "name": "Pattimura",
        "location": "Jl. Mawar No. 227, Semarang",
        "area": 2616
    },
    {
        "certificateNumber": "SHM-0069",
        "name": "Imam Bonjol",
        "location": "Jl. Kenanga No. 234, Yogyakarta",
        "area": 2653
    },
    {
        "certificateNumber": "SHM-0070",
        "name": "Wahidin",
        "location": "Jl. Cendana No. 241, Malang",
        "area": 2690
    },
    {
        "certificateNumber": "SHM-0071",
        "name": "Agus Salim",
        "location": "Jl. Merdeka No. 248, Medan",
        "area": 2727
    },
    {
        "certificateNumber": "SHM-0072",
        "name": "Ki Hajar",
        "location": "Jl. Sudirman No. 5, Makassar",
        "area": 2764
    },
    {
        "certificateNumber": "SHM-0073",
        "name": "Tjokroaminoto",
        "location": "Jl. Diponegoro No. 12, Denpasar",
        "area": 2801
    },
    {
        "certificateNumber": "SHM-0074",
        "name": "Sutomo",
        "location": "Jl. Gajah Mada No. 19, Solo",
        "area": 2838
    },
    {
        "certificateNumber": "SHM-0075",
        "name": "Juanda",
        "location": "Jl. Ahmad Yani No. 26, Cirebon",
        "area": 2875
    },
    {
        "certificateNumber": "SHM-0076",
        "name": "Sjahrir",
        "location": "Jl. Pahlawan No. 33, Jakarta",
        "area": 2512
    },
    {
        "certificateNumber": "SHM-0077",
        "name": "Dewantara",
        "location": "Jl. Melati No. 40, Bogor",
        "area": 2549
    },
    {
        "certificateNumber": "SHM-0078",
        "name": "Ranggawarsita",
        "location": "Jl. Mawar No. 47, Bandung",
        "area": 2586
    },
    {
        "certificateNumber": "SHM-0079",
        "name": "Yos Sudarso",
        "location": "Jl. Kenanga No. 54, Bekasi",
        "area": 2623
    },
    {
        "certificateNumber": "SHM-0080",
        "name": "Pierre Tendean",
        "location": "Jl. Cendana No. 61, Depok",
        "area": 2660
    },
    {
        "certificateNumber": "SHM-0081",
        "name": "Soekarno",
        "location": "Jl. Merdeka No. 68, Tangerang",
        "area": 2697
    },
    {
        "certificateNumber": "SHM-0082",
        "name": "Hatta",
        "location": "Jl. Sudirman No. 75, Surabaya",
        "area": 2734
    },
    {
        "certificateNumber": "SHM-0083",
        "name": "Sudirman",
        "location": "Jl. Diponegoro No. 82, Semarang",
        "area": 2771
    },
    {
        "certificateNumber": "SHM-0084",
        "name": "Kartini",
        "location": "Jl. Gajah Mada No. 89, Yogyakarta",
        "area": 2808
    },
    {
        "certificateNumber": "SHM-0085",
        "name": "Diponegoro",
        "location": "Jl. Ahmad Yani No. 96, Malang",
        "area": 2845
    },
    {
        "certificateNumber": "SHM-0086",
        "name": "Cut Nyak Dien",
        "location": "Jl. Pahlawan No. 103, Medan",
        "area": 2882
    },
    {
        "certificateNumber": "SHM-0087",
        "name": "Hasanuddin",
        "location": "Jl. Melati No. 110, Makassar",
        "area": 2519
    },
    {
        "certificateNumber": "SHM-0088",
        "name": "Pattimura",
        "location": "Jl. Mawar No. 117, Denpasar",
        "area": 2556
    },
    {
        "certificateNumber": "SHM-0089",
        "name": "Imam Bonjol",
        "location": "Jl. Kenanga No. 124, Solo",
        "area": 2593
    },
    {
        "certificateNumber": "SHM-0090",
        "name": "Wahidin",
        "location": "Jl. Cendana No. 131, Cirebon",
        "area": 2630
    },
    {
        "certificateNumber": "SHM-0091",
        "name": "Agus Salim",
        "location": "Jl. Merdeka No. 138, Jakarta",
        "area": 2667
    },
    {
        "certificateNumber": "SHM-0092",
        "name": "Ki Hajar",
        "location": "Jl. Sudirman No. 145, Bogor",
        "area": 2704
    },
    {
        "certificateNumber": "SHM-0093",
        "name": "Tjokroaminoto",
        "location": "Jl. Diponegoro No. 152, Bandung",
        "area": 2741
    },
    {
        "certificateNumber": "SHM-0094",
        "name": "Sutomo",
        "location": "Jl. Gajah Mada No. 159, Bekasi",
        "area": 2778
    },
    {
        "certificateNumber": "SHM-0095",
        "name": "Juanda",
        "location": "Jl. Ahmad Yani No. 166, Depok",
        "area": 2815
    },
    {
        "certificateNumber": "SHM-0096",
        "name": "Sjahrir",
        "location": "Jl. Pahlawan No. 173, Tangerang",
        "area": 2852
    },
    {
        "certificateNumber": "SHM-0097",
        "name": "Dewantara",
        "location": "Jl. Melati No. 180, Surabaya",
        "area": 2889
    },
    {
        "certificateNumber": "SHM-0098",
        "name": "Ranggawarsita",
        "location": "Jl. Mawar No. 187, Semarang",
        "area": 2526
    },
    {
        "certificateNumber": "SHM-0099",
        "name": "Yos Sudarso",
        "location": "Jl. Kenanga No. 194, Yogyakarta",
        "area": 2563
    },
    {
        "certificateNumber": "SHM-0100",
        "name": "Pierre Tendean",
        "location": "Jl. Cendana No. 201, Malang",
        "area": 2600
    },
    {
        "certificateNumber": "SHM-0101",
        "name": "Soekarno",
        "location": "Jl. Merdeka No. 208, Medan",
        "area": 2637
    },
    {
        "certificateNumber": "SHM-0102",
        "name": "Hatta",
        "location": "Jl. Sudirman No. 215, Makassar",
        "area": 2674
    },
    {
        "certificateNumber": "SHM-0103",
        "name": "Sudirman",
        "location": "Jl. Diponegoro No. 222, Denpasar",
        "area": 2711
    },
    {
        "certificateNumber": "SHM-0104",
        "name": "Kartini",
        "location": "Jl. Gajah Mada No. 229, Solo",
        "area": 2748
    },
    {
        "certificateNumber": "SHM-0105",
        "name": "Diponegoro",
        "location": "Jl. Ahmad Yani No. 236, Cirebon",
        "area": 2785
    },
    {
        "certificateNumber": "SHM-0106",
        "name": "Cut Nyak Dien",
        "location": "Jl. Pahlawan No. 243, Jakarta",
        "area": 2822
    },
    {
        "certificateNumber": "SHM-0107",
        "name": "Hasanuddin",
        "location": "Jl. Melati No. 250, Bogor",
        "area": 2859
    },
    {
        "certificateNumber": "SHM-0108",
        "name": "Pattimura",
        "location": "Jl. Mawar No. 7, Bandung",
        "area": 2896
    },
    {
        "certificateNumber": "SHM-0109",
        "name": "Imam Bonjol",
        "location": "Jl. Kenanga No. 14, Bekasi",
        "area": 2533
    },
    {
        "certificateNumber": "SHM-0110",
        "name": "Wahidin",
        "location": "Jl. Cendana No. 21, Depok",
        "area": 2570
    },
    {
        "certificateNumber": "SHM-0111",
        "name": "Agus Salim",
        "location": "Jl. Merdeka No. 28, Tangerang",
        "area": 2607
    },
    {
        "certificateNumber": "SHM-0112",
        "name": "Ki Hajar",
        "location": "Jl. Sudirman No. 35, Surabaya",
        "area": 2644
    },
    {
        "certificateNumber": "SHM-0113",
        "name": "Tjokroaminoto",
        "location": "Jl. Diponegoro No. 42, Semarang",
        "area": 2681
    },
    {
        "certificateNumber": "SHM-0114",
        "name": "Sutomo",
        "location": "Jl. Gajah Mada No. 49, Yogyakarta",
        "area": 2718
    },
    {
        "certificateNumber": "SHM-0115",
        "name": "Juanda",
        "location": "Jl. Ahmad Yani No. 56, Malang",
        "area": 2755
    },
    {
        "certificateNumber": "SHM-0116",
        "name": "Sjahrir",
        "location": "Jl. Pahlawan No. 63, Medan",
        "area": 2792
    },
    {
        "certificateNumber": "SHM-0117",
        "name": "Dewantara",
        "location": "Jl. Melati No. 70, Makassar",
        "area": 2829
    },
    {
        "certificateNumber": "SHM-0118",
        "name": "Ranggawarsita",
        "location": "Jl. Mawar No. 77, Denpasar",
        "area": 2866
    },
    {
        "certificateNumber": "SHM-0119",
        "name": "Yos Sudarso",
        "location": "Jl. Kenanga No. 84, Solo",
        "area": 2503
    },
    {
        "certificateNumber": "SHM-0120",
        "name": "Pierre Tendean",
        "location": "Jl. Cendana No. 91, Cirebon",
        "area": 2540
    },
    {
        "certificateNumber": "SHM-0121",
        "name": "Soekarno",
        "location": "Jl. Merdeka No. 98, Jakarta",
        "area": 2577
    }
]
